snippet/__init__.py
snippet/plugin.py
mkdocs_snippet_plugin-1.0.2.dist-info/LICENSE
mkdocs_snippet_plugin-1.0.2.dist-info/METADATA
mkdocs_snippet_plugin-1.0.2.dist-info/WHEEL
mkdocs_snippet_plugin-1.0.2.dist-info/entry_points.txt
mkdocs_snippet_plugin-1.0.2.dist-info/top_level.txt
mkdocs_snippet_plugin-1.0.2.dist-info/RECORD
