Metadata-Version: 2.1
Name: mkdocs-snippet-plugin
Version: 1.0.2
Summary: An mkdocs plugin that injects snippets from a file in a git repository
Home-page: https://github.com/mprivat/mkdocs-snippet-plugin
Author: Michael Privat
Author-email: Michael.Privat@availity.com
License: MIT
Keywords: mkdocs python markdown snippet
Platform: UNKNOWN
Classifier: Development Status :: 5 - Production/Stable
Classifier: Intended Audience :: Developers
Classifier: Intended Audience :: Information Technology
Classifier: License :: OSI Approved :: MIT License
Classifier: Programming Language :: Python
Classifier: Programming Language :: Python :: 2
Classifier: Programming Language :: Python :: 2.7
Classifier: Programming Language :: Python :: 3
Classifier: Programming Language :: Python :: 3.4
Classifier: Programming Language :: Python :: 3.5
Classifier: Programming Language :: Python :: 3.6
Classifier: Programming Language :: Python :: 3.7
Requires-Python: >=2.7.9,!=3.0.*,!=3.1.*,!=3.2.*,!=3.3.*
Requires-Dist: mkdocs (>=0.17)
Requires-Dist: gitpython
